WkDB/WkDB.py
WkDB/__init__.py
WkDB-1.1.0.1.dist-info/LICENSE
WkDB-1.1.0.1.dist-info/METADATA
WkDB-1.1.0.1.dist-info/WHEEL
WkDB-1.1.0.1.dist-info/top_level.txt
WkDB-1.1.0.1.dist-info/RECORD
