Metadata-Version: 2.1
Name: WkDB
Version: 1.1.0.1
Summary: WkDB对pymysql和sqlite3进行了封装，提供常用的增删改查操作，简化操作。
Home-page: https://gitee.com/purify_wang/wk-db.git
Author: WANGKANG
Author-email: 1686617586@qq.com
License: GPL-2.0
Platform: all
Classifier: Intended Audience :: Developers
Classifier: Operating System :: OS Independent
Classifier: Natural Language :: Chinese (Simplified)
Classifier: Programming Language :: Python
Classifier: Programming Language :: Python :: 3
Classifier: Programming Language :: Python :: 3.10
Classifier: Programming Language :: Python :: 3.11
Classifier: Programming Language :: Python :: 3.12
Classifier: Topic :: Software Development :: Libraries
Requires-Python: >=3.10.0
License-File: LICENSE
Requires-Dist: WkLog
Requires-Dist: pymysql
